jot/__init__.py
jot/rollbar.py
dl_jot_rollbar-0.1.dist-info/WHEEL
dl_jot_rollbar-0.1.dist-info/METADATA
dl_jot_rollbar-0.1.dist-info/RECORD
