Metadata-Version: 2.1
Name: dl-jot-rollbar
Version: 0.1
Summary: A Jot target that reports errors to Rollbar
License: MIT
Author-email: Colin Putney <colin.putney@descarteslabs.com>
Requires-Python: >=3.7
Requires-Dist: dl-jot>=0.1
Requires-Dist: rollbar>=0.16.2
